input_monitor/__init__.py
input_monitor/__main__.py
input_monitor/app.py
input_monitor/version.py
input_monitor/images/mouse-left-click.png
input_monitor/images/mouse-middle-click.png
input_monitor/images/mouse-right-click.png
input_monitor/images/windows-10-logo.png
input_monitor-1.0.0.dist-info/licenses/LICENSE
input_monitor-1.0.0.dist-info/METADATA
input_monitor-1.0.0.dist-info/WHEEL
input_monitor-1.0.0.dist-info/entry_points.txt
input_monitor-1.0.0.dist-info/top_level.txt
input_monitor-1.0.0.dist-info/RECORD
