Metadata-Version: 2.4
Name: input-monitor
Version: 1.0.0
Summary: An on-screen input & mouse tracker widget
Author-email: jabezwinston <jabezwinston@gmail.com>
License-Expression: GPL-3.0-or-later
Project-URL: Homepage, https://github.com/zion-school/input-monitor
Keywords: input,monitor,widget,mouse,keyboard
Classifier: Programming Language :: Python :: 3
Classifier: Programming Language :: Python :: 3 :: Only
Classifier: Operating System :: Microsoft :: Windows
Classifier: Operating System :: POSIX :: Linux
Requires-Python: >=3.8
License-File: LICENSE
Requires-Dist: pynput>=1.7
Requires-Dist: keyboard>=0.13
Dynamic: license-file
